pde_rk/__init__.py
pde_rk/pde.py
pde_rk-0.1.4.dist-info/LICENSE
pde_rk-0.1.4.dist-info/METADATA
pde_rk-0.1.4.dist-info/WHEEL
pde_rk-0.1.4.dist-info/top_level.txt
pde_rk-0.1.4.dist-info/RECORD
