Metadata-Version: 2.1
Name: pde-rk
Version: 0.1.4
Summary: Package for simulating one-dimensional PDE models with and adaptive Runge-Kutta scheme
Author: Tom Bland
Author-email: tom_bland@hotmail.co.uk
License: CC BY 4.0
Project-URL: Source Code, https://github.com/tsmbland/pde-rk
License-File: LICENSE
Requires-Dist: numpy
